fastapi_simple_auth_dark/__init__.py
fastapi_simple_auth_dark/statics/css/styles.css
fastapi_simple_auth_dark/statics/images/github-mark.svg
fastapi_simple_auth_dark/statics/js/simpleauth.js
fastapi_simple_auth_dark/templates/afterlogin.html
fastapi_simple_auth_dark/templates/base.html
fastapi_simple_auth_dark/templates/login.html
fastapi_simple_auth_dark/templates/profile.html
fastapi_simple_auth_dark/templates/recover.html
fastapi_simple_auth_dark/templates/recover_code.html
fastapi_simple_auth_dark/templates/register.html
fastapi_simple_auth_dark/templates/verify-email.html
fastapi_simple_auth_dark/templates/email/change-email.html
fastapi_simple_auth_dark/templates/email/confirm-email.html
fastapi_simple_auth_dark/templates/email/recover.html
fastapi_simple_auth_dark-0.0.6.dist-info/METADATA
fastapi_simple_auth_dark-0.0.6.dist-info/WHEEL
fastapi_simple_auth_dark-0.0.6.dist-info/licenses/LICENSE
fastapi_simple_auth_dark-0.0.6.dist-info/RECORD
