Metadata-Version: 2.3
Name: fastapi-simple-auth-dark
Version: 0.0.6
Summary: FastAPI simple authentication (basic DARK theme)
Project-URL: Documentation, https://github.com/yaroslaff/fastapi-simple-auth#readme
Project-URL: Issues, https://github.com/yaroslaff/fastapi-simple-auth/issues
Project-URL: Source, https://github.com/yaroslaff/fastapi-simple-auth
Author-email: Yaroslav Polyakov <yaroslaff@gmail.com>
License-Expression: MIT
License-File: LICENSE
Classifier: Development Status :: 4 - Beta
Classifier: Programming Language :: Python
Classifier: Programming Language :: Python :: 3.7
Classifier: Programming Language :: Python :: 3.8
Classifier: Programming Language :: Python :: 3.9
Classifier: Programming Language :: Python :: 3.10
Classifier: Programming Language :: Python :: 3.11
Classifier: Programming Language :: Python :: Implementation :: CPython
Classifier: Programming Language :: Python :: Implementation :: PyPy
Requires-Python: >=3.7
